README.md
license
setup.py
excel_to_dataframe/__init__.py
excel_to_dataframe/example.py
excel_to_dataframe/excel_to_df.dll
excel_to_dataframe/excel_to_df.so
excel_to_dataframe/excel_to_pandas.py
excel_to_dataframe.egg-info/PKG-INFO
excel_to_dataframe.egg-info/SOURCES.txt
excel_to_dataframe.egg-info/dependency_links.txt
excel_to_dataframe.egg-info/requires.txt
excel_to_dataframe.egg-info/top_level.txt